robotpy_apriltag/__init__.py
robotpy_apriltag/py.typed
robotpy_apriltag/version.py
robotpy_apriltag/src/main.cpp
robotpy_apriltag/_apriltag.cpython-311-darwin.so
robotpy_apriltag/_apriltag.pyi
robotpy_apriltag/_init__apriltag.py
robotpy_apriltag/apriltag.pc
robotpy_apriltag/trampolines/frc__AprilTag.hpp
robotpy_apriltag/trampolines/frc__AprilTagDetection.hpp
robotpy_apriltag/trampolines/frc__AprilTagDetection__Point.hpp
robotpy_apriltag/trampolines/frc__AprilTagDetector.hpp
robotpy_apriltag/trampolines/frc__AprilTagDetector__Config.hpp
robotpy_apriltag/trampolines/frc__AprilTagDetector__QuadThresholdParameters.hpp
robotpy_apriltag/trampolines/frc__AprilTagDetector__Results.hpp
robotpy_apriltag/trampolines/frc__AprilTagFieldLayout.hpp
robotpy_apriltag/trampolines/frc__AprilTagPoseEstimate.hpp
robotpy_apriltag/trampolines/frc__AprilTagPoseEstimator.hpp
robotpy_apriltag/trampolines/frc__AprilTagPoseEstimator__Config.hpp
robotpy_apriltag-2025.3.2.3.dist-info/METADATA
robotpy_apriltag-2025.3.2.3.dist-info/WHEEL
robotpy_apriltag-2025.3.2.3.dist-info/entry_points.txt
robotpy_apriltag-2025.3.2.3.dist-info/RECORD
